ctk_color_picker_alpha/__init__.py
ctk_color_picker_alpha/ask_color/__init__.py
ctk_color_picker_alpha/ask_color/ctk_color_picker.py
ctk_color_picker_alpha/color_wheel.png
ctk_color_picker_alpha/components/__init__.py
ctk_color_picker_alpha/components/my_ctk_components.py
ctk_color_picker_alpha/driver.py
ctk_color_picker_alpha/target.png
ctk_color_picker_alpha/transparent_background.png
ctk_color_picker_alpha/util/__init__.py
ctk_color_picker_alpha/util/exp_image_blend.py
ctk_color_picker_alpha/util/my_util.py
ctk_color_picker_alpha/widget/__init__.py
ctk_color_picker_alpha/widget/ctk_color_picker_widget.py
ctk_color_picker_alpha-0.8.9.dist-info/LICENSE
ctk_color_picker_alpha-0.8.9.dist-info/METADATA
ctk_color_picker_alpha-0.8.9.dist-info/WHEEL
ctk_color_picker_alpha-0.8.9.dist-info/RECORD
