Metadata-Version: 2.1
Name: ctk-color-picker-alpha
Version: 0.8.9
Summary: An eight-digits hex code color picker, with alpha value.
License: CC0 1.0 Universal
Author: Kolyn Lin
Author-email: Kanzakimakai27875628@gmail.com
Requires-Python: >=3.11,<4.0
Classifier: License :: Other/Proprietary License
Classifier: Programming Language :: Python :: 3
Classifier: Programming Language :: Python :: 3.11
Classifier: Programming Language :: Python :: 3.12
Requires-Dist: customtkinter (==5.2.2)
Requires-Dist: numpy (==1.26.4)
Requires-Dist: pillow (==10.3.0)
